{
    "/js/vendor.js": "/js/vendor.js?id=c581dd0b367a0c8d4040",
    "/js/app.js": "/js/app.js?id=aa4fc3f5d62962e00c93",
    "/js/usuario.js": "/js/usuario.js?id=02bd4a4ebcc92b3620f4",
    "/js/perfil.js": "/js/perfil.js?id=b4d52076be2d2fe93c07",
    "/js/disciplina.js": "/js/disciplina.js?id=b4234c0dc87549263d84",
    "/js/permissao.js": "/js/permissao.js?id=34e2882fba591b316c44",
    "/css/bootstrap.css": "/css/bootstrap.css?id=78741621eaee42bace4d",
    "/css/select2.css": "/css/select2.css?id=fd9fe49d3d919d631d3e",
    "/css/fonts.css": "/css/fonts.css?id=0ff9b3d1902637f31598",
    "/css/bootstrap.css.map": "/css/bootstrap.css.map?id=b2f407b1aa09ede22e8a"
}